SqltDAO/CrudMeister.py
SqltDAO/Demo123.py
SqltDAO/Ledger.py
SqltDAO/MainGUI.py
SqltDAO/UpdateTestCase.py
SqltDAO/__init__.py
SqltDAO/main.py
SqltDAO/CodeGen01/CodeGen.py
SqltDAO/CodeGen01/CodeLevel.py
SqltDAO/CodeGen01/DaoExceptions.py
SqltDAO/CodeGen01/Meta.py
SqltDAO/CodeGen01/Normalizers.py
SqltDAO/CodeGen01/OrderClass.py
SqltDAO/CodeGen01/SqlSyntax.py
SqltDAO/CodeGen01/TextDataDetector.py
SqltDAO/DaoTest01/GenNasdaq.py
SqltDAO/DaoTest01/GenNasdaqTest.py
SqltDAO/DaoTest01/Income.py
SqltDAO/DaoTest01/NasdaqDAO.py
SqltDAO/DaoTest01/foo.py
SqltDAO/DaoTest01/tc001_driver.py
SqltDAO/DaoTest01/tc001_gen.py
SqltDAO/GenGUI/Data2Code.py
SqltDAO/GenGUI/DataAI.py
SqltDAO/GenGUI/DataFrameOne.py
SqltDAO/GenGUI/DataPreferences.py
SqltDAO/GenGUI/StandardEntry.py
SqltDAO/GenGUI/TableDef.py
SqltDAO/GenTUI/TuiMain.py
SqltDAO/SchemaDef/DataDetective.py
SqltDAO/SchemaDef/Factory.py
SqltDAO/SchemaDef/OrderDef.py
SqltDAO/SchemaDef/Table.py
PyDAO_9000-1.5.0.dist-info/LICENSE
PyDAO_9000-1.5.0.dist-info/METADATA
PyDAO_9000-1.5.0.dist-info/WHEEL
PyDAO_9000-1.5.0.dist-info/top_level.txt
PyDAO_9000-1.5.0.dist-info/RECORD
