Metadata-Version: 2.1
Name: PyDAO-9000
Version: 1.5.0
Summary: 'All-In-One File' SQL Code Generator
Author-email: Randall Nagy <r.a.nagy@gmail.com>
Project-URL: Homepage, https://github.com/soft9000/PyDAO
Project-URL: Bug Tracker, https://github.com/soft9000/PyDAO/issues
Classifier: Programming Language :: Python :: 3
Classifier: License :: OSI Approved :: MIT License
Classifier: Operating System :: OS Independent
Requires-Python: >=3.6
License-File: LICENSE
